cmd_ai/__init__.py
cmd_ai/config.py
cmd_ai/llm.py
cmd_ai/main.py
ai_bash-0.1.3.2.dist-info/METADATA
ai_bash-0.1.3.2.dist-info/WHEEL
ai_bash-0.1.3.2.dist-info/entry_points.txt
ai_bash-0.1.3.2.dist-info/licenses/LICENSE
ai_bash-0.1.3.2.dist-info/RECORD
