Metadata-Version: 2.4
Name: ai_bash
Version: 0.1.3.2
Summary: An AI tool that converts natural language requests into command line commands(一个将自然语言需求转换为命令行命令的AI工具)
License: MIT
License-File: LICENSE
Requires-Python: >=3.8
Requires-Dist: click>=8.1.0
Requires-Dist: openai>=1.0.0
Requires-Dist: python-dotenv>=1.0.0
